polarcle/__init__.py
polarcle-0.2.1.dist-info/METADATA
polarcle-0.2.1.dist-info/WHEEL
polarcle-0.2.1.dist-info/RECORD
