Metadata-Version: 2.3
Name: polarcle
Version: 0.2.1
Summary: Polars Dataframe integration with Oracle
Author-email: iwolf <isaacwolfsite@gmail.com>
Requires-Python: >=3.12
Requires-Dist: oracledb
Requires-Dist: polars
